{
  "annotations": {
    "list": [
      {
        "builtIn": 1,
        "datasource": "-- Grafana --",
        "enable": true,
        "hide": true,
        "iconColor": "rgba(0, 211, 255, 1)",
        "name": "Annotations & Alerts",
        "target": {
          "limit": 100,
          "matchAny": false,
          "tags": [],
          "type": "dashboard"
        },
        "type": "dashboard"
      }
    ]
  },
  "editable": true,
  "fiscalYearStartMonth": 0,
  "graphTooltip": 0,
  "id": 1,
  "links": [],
  "liveNow": false,
  "panels": [
    {
      "fieldConfig": {
        "defaults": {
          "color": {
            "mode": "palette-classic"
          },
          "custom": {
            "axisLabel": "",
            "axisPlacement": "auto",
            "barAlignment": 0,
            "drawStyle": "line",
            "fillOpacity": 0,
            "gradientMode": "none",
            "hideFrom": {
              "legend": false,
              "tooltip": false,
              "viz": false
            },
            "lineInterpolation": "linear",
            "lineWidth": 1,
            "pointSize": 5,
            "scaleDistribution": {
              "type": "linear"
            },
            "showPoints": "auto",
            "spanNulls": false,
            "stacking": {
              "group": "A",
              "mode": "none"
            },
            "thresholdsStyle": {
              "mode": "off"
            }
          },
          "decimals": 2,
          "mappings": [],
          "thresholds": {
            "mode": "absolute",
            "steps": [
              {
                "color": "green",
                "value": null
              },
              {
                "color": "red",
                "value": 80
              }
            ]
          },
          "unit": "percent"
        },
        "overrides": []
      },
      "gridPos": {
        "h": 7,
        "w": 13,
        "x": 0,
        "y": 0
      },
      "id": 2,
      "options": {
        "legend": {
          "calcs": [
            "mean",
            "lastNotNull"
          ],
          "displayMode": "table",
          "placement": "bottom"
        },
        "tooltip": {
          "mode": "single",
          "sort": "none"
        }
      },
      "targets": [
        {
          "datasource": {
            "type": "prometheus",
            "uid": "PBFA97CFB590B2093"
          },
          "exemplar": true,
          "expr": "rate(process_cpu_seconds_total{job=\"flask-app\"}[30s])",
          "interval": "",
          "legendFormat": "{{job}}",
          "refId": "A"
        }
      ],
      "title": "CPU Utilisation",
      "type": "timeseries"
    },
    {
      "fieldConfig": {
        "defaults": {
          "color": {
            "mode": "palette-classic"
          },
          "custom": {
            "axisLabel": "",
            "axisPlacement": "auto",
            "barAlignment": 0,
            "drawStyle": "line",
            "fillOpacity": 0,
            "gradientMode": "none",
            "hideFrom": {
              "legend": false,
              "tooltip": false,
              "viz": false
            },
            "lineInterpolation": "linear",
            "lineWidth": 1,
            "pointSize": 5,
            "scaleDistribution": {
              "type": "linear"
            },
            "showPoints": "auto",
            "spanNulls": false,
            "stacking": {
              "group": "A",
              "mode": "none"
            },
            "thresholdsStyle": {
              "mode": "off"
            }
          },
          "mappings": [],
          "thresholds": {
            "mode": "absolute",
            "steps": [
              {
                "color": "green",
                "value": null
              },
              {
                "color": "red",
                "value": 80
              }
            ]
          },
          "unit": "bytes"
        },
        "overrides": []
      },
      "gridPos": {
        "h": 7,
        "w": 11,
        "x": 13,
        "y": 0
      },
      "id": 4,
      "options": {
        "legend": {
          "calcs": [
            "lastNotNull",
            "mean"
          ],
          "displayMode": "table",
          "placement": "bottom"
        },
        "tooltip": {
          "mode": "single",
          "sort": "none"
        }
      },
      "targets": [
        {
          "datasource": {
            "type": "prometheus",
            "uid": "PBFA97CFB590B2093"
          },
          "exemplar": true,
          "expr": "process_resident_memory_bytes{job=\"flask-app\"}",
          "interval": "",
          "legendFormat": "{{job}}",
          "refId": "A"
        }
      ],
      "title": "Memory Usage",
      "type": "timeseries"
    },
    {
      "description": "",
      "fieldConfig": {
        "defaults": {
          "color": {
            "mode": "palette-classic"
          },
          "custom": {
            "axisLabel": "",
            "axisPlacement": "auto",
            "barAlignment": 0,
            "drawStyle": "line",
            "fillOpacity": 0,
            "gradientMode": "none",
            "hideFrom": {
              "legend": false,
              "tooltip": false,
              "viz": false
            },
            "lineInterpolation": "linear",
            "lineWidth": 1,
            "pointSize": 5,
            "scaleDistribution": {
              "type": "linear"
            },
            "showPoints": "auto",
            "spanNulls": false,
            "stacking": {
              "group": "A",
              "mode": "none"
            },
            "thresholdsStyle": {
              "mode": "off"
            }
          },
          "mappings": [],
          "thresholds": {
            "mode": "absolute",
            "steps": [
              {
                "color": "green",
                "value": null
              },
              {
                "color": "red",
                "value": 80
              }
            ]
          }
        },
        "overrides": []
      },
      "gridPos": {
        "h": 6,
        "w": 24,
        "x": 0,
        "y": 7
      },
      "id": 6,
      "options": {
        "legend": {
          "calcs": [
            "mean"
          ],
          "displayMode": "table",
          "placement": "right"
        },
        "tooltip": {
          "mode": "single",
          "sort": "none"
        }
      },
      "targets": [
        {
          "datasource": {
            "type": "prometheus",
            "uid": "PBFA97CFB590B2093"
          },
          "exemplar": true,
          "expr": "rate(flask_http_request_duration_seconds_count{status=\"200\"}[30s])",
          "interval": "",
          "legendFormat": "{{path}}",
          "refId": "A"
        }
      ],
      "title": "Requests per Second",
      "type": "timeseries"
    },
    {
      "fieldConfig": {
        "defaults": {
          "color": {
            "mode": "palette-classic"
          },
          "custom": {
            "axisLabel": "",
            "axisPlacement": "auto",
            "barAlignment": 0,
            "drawStyle": "line",
            "fillOpacity": 0,
            "gradientMode": "none",
            "hideFrom": {
              "legend": false,
              "tooltip": false,
              "viz": false
            },
            "lineInterpolation": "linear",
            "lineWidth": 1,
            "pointSize": 5,
            "scaleDistribution": {
              "type": "linear"
            },
            "showPoints": "auto",
            "spanNulls": false,
            "stacking": {
              "group": "A",
              "mode": "none"
            },
            "thresholdsStyle": {
              "mode": "off"
            }
          },
          "mappings": [],
          "thresholds": {
            "mode": "absolute",
            "steps": [
              {
                "color": "green",
                "value": null
              },
              {
                "color": "red",
                "value": 80
              }
            ]
          }
        },
        "overrides": []
      },
      "gridPos": {
        "h": 6,
        "w": 24,
        "x": 0,
        "y": 13
      },
      "id": 8,
      "options": {
        "legend": {
          "calcs": [
            "max",
            "mean"
          ],
          "displayMode": "table",
          "placement": "right"
        },
        "tooltip": {
          "mode": "single",
          "sort": "none"
        }
      },
      "targets": [
        {
          "datasource": {
            "type": "prometheus",
            "uid": "PBFA97CFB590B2093"
          },
          "exemplar": true,
          "expr": "increase(flask_http_request_total[1m])",
          "interval": "",
          "legendFormat": "HTTP {{ method }} {{ status }}",
          "refId": "A"
        }
      ],
      "title": "Total Requests per Minute",
      "type": "timeseries"
    },
    {
      "fieldConfig": {
        "defaults": {
          "color": {
            "mode": "palette-classic"
          },
          "custom": {
            "axisLabel": "",
            "axisPlacement": "auto",
            "barAlignment": 0,
            "drawStyle": "line",
            "fillOpacity": 0,
            "gradientMode": "none",
            "hideFrom": {
              "legend": false,
              "tooltip": false,
              "viz": false
            },
            "lineInterpolation": "linear",
            "lineWidth": 1,
            "pointSize": 5,
            "scaleDistribution": {
              "type": "linear"
            },
            "showPoints": "auto",
            "spanNulls": false,
            "stacking": {
              "group": "A",
              "mode": "none"
            },
            "thresholdsStyle": {
              "mode": "off"
            }
          },
          "mappings": [],
          "thresholds": {
            "mode": "absolute",
            "steps": [
              {
                "color": "green",
                "value": null
              },
              {
                "color": "red",
                "value": 80
              }
            ]
          },
          "unit": "s"
        },
        "overrides": []
      },
      "gridPos": {
        "h": 8,
        "w": 24,
        "x": 0,
        "y": 19
      },
      "id": 10,
      "options": {
        "legend": {
          "calcs": [
            "max",
            "mean"
          ],
          "displayMode": "table",
          "placement": "right"
        },
        "tooltip": {
          "mode": "single",
          "sort": "none"
        }
      },
      "targets": [
        {
          "datasource": {
            "type": "prometheus",
            "uid": "PBFA97CFB590B2093"
          },
          "exemplar": true,
          "expr": "rate(flask_http_request_duration_seconds_sum{status=\"200\"}[30s])\n/ rate(flask_http_request_duration_seconds_count{status=\"200\"}[30s])",
          "interval": "",
          "legendFormat": "2xx {{ method }}: {{ path }}",
          "refId": "A"
        },
        {
          "datasource": {
            "type": "prometheus",
            "uid": "PBFA97CFB590B2093"
          },
          "exemplar": true,
          "expr": "rate(flask_http_request_duration_seconds_sum{status=~\"4.+\"}[30s])\n/ rate(flask_http_request_duration_seconds_count{status=\"4.+\"}[30s])",
          "hide": false,
          "interval": "",
          "legendFormat": "4xx {{ method }}: {{ path }}",
          "refId": "B"
        },
        {
          "datasource": {
            "type": "prometheus",
            "uid": "PBFA97CFB590B2093"
          },
          "exemplar": true,
          "expr": "rate(flask_http_request_duration_seconds_sum{status=~\"5.+\"}[30s])\n/ rate(flask_http_request_duration_seconds_count{status=\"5.+\"}[30s])",
          "hide": false,
          "interval": "",
          "legendFormat": "5xx {{ method }}: {{ path }}",
          "refId": "C"
        }
      ],
      "title": "Average Response Time [30s]",
      "type": "timeseries"
    },
    {
      "fieldConfig": {
        "defaults": {
          "color": {
            "mode": "palette-classic"
          },
          "custom": {
            "axisLabel": "",
            "axisPlacement": "auto",
            "barAlignment": 0,
            "drawStyle": "line",
            "fillOpacity": 0,
            "gradientMode": "none",
            "hideFrom": {
              "legend": false,
              "tooltip": false,
              "viz": false
            },
            "lineInterpolation": "linear",
            "lineWidth": 1,
            "pointSize": 5,
            "scaleDistribution": {
              "type": "linear"
            },
            "showPoints": "auto",
            "spanNulls": false,
            "stacking": {
              "group": "A",
              "mode": "none"
            },
            "thresholdsStyle": {
              "mode": "off"
            }
          },
          "mappings": [],
          "thresholds": {
            "mode": "absolute",
            "steps": [
              {
                "color": "green",
                "value": null
              },
              {
                "color": "red",
                "value": 80
              }
            ]
          }
        },
        "overrides": []
      },
      "gridPos": {
        "h": 7,
        "w": 24,
        "x": 0,
        "y": 27
      },
      "id": 11,
      "options": {
        "legend": {
          "calcs": [
            "max",
            "mean"
          ],
          "displayMode": "table",
          "placement": "right"
        },
        "tooltip": {
          "mode": "single",
          "sort": "none"
        }
      },
      "targets": [
        {
          "datasource": {
            "type": "prometheus",
            "uid": "PBFA97CFB590B2093"
          },
          "exemplar": true,
          "expr": "sum(rate(flask_http_request_duration_seconds_count{status!=\"200\"}[30s]))",
          "interval": "",
          "legendFormat": "HTTP {{ method }} {{ status }}",
          "refId": "A"
        }
      ],
      "title": "Errors per Second",
      "type": "timeseries"
    },
    {
      "fieldConfig": {
        "defaults": {
          "color": {
            "mode": "palette-classic"
          },
          "custom": {
            "axisLabel": "",
            "axisPlacement": "auto",
            "barAlignment": 0,
            "drawStyle": "line",
            "fillOpacity": 0,
            "gradientMode": "none",
            "hideFrom": {
              "legend": false,
              "tooltip": false,
              "viz": false
            },
            "lineInterpolation": "linear",
            "lineWidth": 1,
            "pointSize": 5,
            "scaleDistribution": {
              "type": "linear"
            },
            "showPoints": "auto",
            "spanNulls": false,
            "stacking": {
              "group": "A",
              "mode": "none"
            },
            "thresholdsStyle": {
              "mode": "off"
            }
          },
          "mappings": [],
          "thresholds": {
            "mode": "absolute",
            "steps": [
              {
                "color": "green",
                "value": null
              },
              {
                "color": "red",
                "value": 80
              }
            ]
          }
        },
        "overrides": []
      },
      "gridPos": {
        "h": 6,
        "w": 24,
        "x": 0,
        "y": 34
      },
      "id": 13,
      "options": {
        "legend": {
          "calcs": [
            "max",
            "mean"
          ],
          "displayMode": "table",
          "placement": "right"
        },
        "tooltip": {
          "mode": "single",
          "sort": "none"
        }
      },
      "targets": [
        {
          "datasource": {
            "type": "prometheus",
            "uid": "PBFA97CFB590B2093"
          },
          "exemplar": true,
          "expr": "increase(flask_http_request_duration_seconds_bucket{status=\"200\",le=\"0.25\"}[30s]) / ignoring (le) increase(flask_http_request_duration_seconds_count{status=\"200\"}[30s])",
          "interval": "",
          "legendFormat": "{{ method }}: {{ path }}",
          "refId": "A"
        }
      ],
      "title": "Requests under 250ms",
      "type": "timeseries"
    },
    {
      "fieldConfig": {
        "defaults": {
          "color": {
            "mode": "palette-classic"
          },
          "custom": {
            "axisLabel": "",
            "axisPlacement": "auto",
            "barAlignment": 0,
            "drawStyle": "line",
            "fillOpacity": 0,
            "gradientMode": "none",
            "hideFrom": {
              "legend": false,
              "tooltip": false,
              "viz": false
            },
            "lineInterpolation": "linear",
            "lineWidth": 1,
            "pointSize": 5,
            "scaleDistribution": {
              "type": "linear"
            },
            "showPoints": "auto",
            "spanNulls": false,
            "stacking": {
              "group": "A",
              "mode": "none"
            },
            "thresholdsStyle": {
              "mode": "off"
            }
          },
          "decimals": 2,
          "mappings": [],
          "thresholds": {
            "mode": "absolute",
            "steps": [
              {
                "color": "green",
                "value": null
              },
              {
                "color": "red",
                "value": 80
              }
            ]
          }
        },
        "overrides": []
      },
      "gridPos": {
        "h": 6,
        "w": 24,
        "x": 0,
        "y": 40
      },
      "id": 14,
      "options": {
        "legend": {
          "calcs": [
            "max",
            "mean"
          ],
          "displayMode": "table",
          "placement": "right"
        },
        "tooltip": {
          "mode": "single",
          "sort": "none"
        }
      },
      "targets": [
        {
          "datasource": {
            "type": "prometheus",
            "uid": "PBFA97CFB590B2093"
          },
          "exemplar": true,
          "expr": "histogram_quantile(0.9, rate(flask_http_request_duration_seconds_bucket{status=\"200\"}[30s]))",
          "interval": "",
          "legendFormat": "{{ method }}: {{ path }}",
          "refId": "A"
        }
      ],
      "title": "Request duration [s] - p90",
      "type": "timeseries"
    },
    {
      "fieldConfig": {
        "defaults": {
          "color": {
            "mode": "palette-classic"
          },
          "custom": {
            "axisLabel": "",
            "axisPlacement": "auto",
            "barAlignment": 0,
            "drawStyle": "line",
            "fillOpacity": 0,
            "gradientMode": "none",
            "hideFrom": {
              "legend": false,
              "tooltip": false,
              "viz": false
            },
            "lineInterpolation": "linear",
            "lineWidth": 1,
            "pointSize": 5,
            "scaleDistribution": {
              "type": "linear"
            },
            "showPoints": "auto",
            "spanNulls": false,
            "stacking": {
              "group": "A",
              "mode": "none"
            },
            "thresholdsStyle": {
              "mode": "off"
            }
          },
          "decimals": 2,
          "mappings": [],
          "thresholds": {
            "mode": "absolute",
            "steps": [
              {
                "color": "green",
                "value": null
              },
              {
                "color": "red",
                "value": 80
              }
            ]
          }
        },
        "overrides": []
      },
      "gridPos": {
        "h": 6,
        "w": 24,
        "x": 0,
        "y": 46
      },
      "id": 15,
      "options": {
        "legend": {
          "calcs": [
            "max",
            "mean"
          ],
          "displayMode": "table",
          "placement": "right"
        },
        "tooltip": {
          "mode": "single",
          "sort": "none"
        }
      },
      "targets": [
        {
          "datasource": {
            "type": "prometheus",
            "uid": "PBFA97CFB590B2093"
          },
          "exemplar": true,
          "expr": "histogram_quantile(0.5, rate(flask_http_request_duration_seconds_bucket{status=\"200\"}[30s]))",
          "interval": "",
          "legendFormat": "{{ method }}: {{ path }}",
          "refId": "A"
        }
      ],
      "title": "Request duration [s] - p50",
      "type": "timeseries"
    }
  ],
  "schemaVersion": 35,
  "style": "dark",
  "tags": [],
  "templating": {
    "list": []
  },
  "time": {
    "from": "now-15m",
    "to": "now"
  },
  "timepicker": {},
  "timezone": "",
  "title": "Application Metrics",
  "uid": "j0VZzcy7z",
  "version": 3,
  "weekStart": ""
}
